setup.py
mrt/__init__.py
mrt/args.py
mrt/block.py
mrt/general_functions.py
mrt/main.py
mrt/mrt_hist_seq_length.py
mrt/project.py
mrt/sourcefile.py
mrt/sourcefileline.py
mrt.egg-info/PKG-INFO
mrt.egg-info/SOURCES.txt
mrt.egg-info/dependency_links.txt
mrt.egg-info/entry_points.txt
mrt.egg-info/requires.txt
mrt.egg-info/top_level.txt
mrt/test/__init__.py
mrt/test/test_args.py
mrt/test/test_general_functions.py
mrt/test/test_project.py
mrt/test/features/steps/steps_general.py