Metadata-Version: 1.0
Name: mrt
Version: 0.1.3
Summary: Mothur reporting tool
Home-page: http://bitbucket.org/pieterb/mrt/
Author: Pieter B.
Author-email: pbu_mrt@zoho.com
License: BSD
Keywords: Mothur literate programming reproducible research
Platform: UNKNOWN
Classifier: Development Status :: 3 - Alpha
Classifier: Environment :: Console
Classifier: Intended Audience :: Science/Research
Classifier: License :: Public Domain
Classifier: Natural Language :: English
Classifier: Operating System :: POSIX :: Linux
Classifier: Programming Language :: Python
Classifier: Topic :: Scientific/Engineering :: Bio-Informatics
Classifier: Topic :: Software Development :: Documentation
